{
  "books": [
    {
      "isbn": "qqqqq",
      "title": "Cool Book",
      "authors": "zzzz aaaa",
      "published": "12344",
      "description": "lorem ipsum",
      "coverImage": "https://freedesignfile.com/upload/2015/06/Brochure-and-book-cover-creative-vector-06.jpg",
      "id": 11
    },
    {
      "isbn": "aaaaaa",
      "title": "aaaaaaaa",
      "authors": "aaaaaaaa",
      "published": "aaaaaaaa",
      "description": "aaaaaaaaaaa",
      "coverImage": "https://c7.uihere.com/files/178/590/572/playing-card-ace-of-hearts-one-card-suit-heart-playing-cards.jpg",
      "id": 13
    },
    {
      "isbn": "mmmm",
      "title": "mmmm",
      "authors": "jjjjj",
      "published": "76566gb",
      "description": "hhhhh",
      "coverImage": "https://upload.wikimedia.org/wikipedia/en/thumb/d/d8/Cover_Cool_it_low_res.jpg/220px-Cover_Cool_it_low_res.jpg",
      "id": 14
    },
    {
      "isbn": "mmmm",
      "title": "mmmm",
      "authors": "jjjjj",
      "published": "76566gb",
      "description": "hhhhh",
      "coverImage": "https://upload.wikimedia.org/wikipedia/en/thumb/d/d8/Cover_Cool_it_low_res.jpg/220px-Cover_Cool_it_low_res.jpg",
      "id": 15
    },
    {
      "isbn": "mmmm",
      "title": "aaaaaaaa",
      "authors": "jjjjj",
      "published": "76566gb",
      "description": "hhhhh",
      "coverImage": "https://upload.wikimedia.org/wikipedia/en/thumb/d/d8/Cover_Cool_it_low_res.jpg/220px-Cover_Cool_it_low_res.jpg",
      "id": 16
    }
  ]
}